glinski/_Board.py
glinski/__init__.py
glinski/_vectors.py
glinski/_enums/PlayerColor.py
glinski/_enums/__init__.py
glinski/_enums/pieces.py
glinski/_enums/cells/Cell.py
glinski/_enums/cells/CellColor.py
glinski/_enums/cells/Column.py
glinski/_enums/cells/__init__.py
glinski-0.4.0.dist-info/LICENSE.txt
glinski-0.4.0.dist-info/METADATA
glinski-0.4.0.dist-info/WHEEL
glinski-0.4.0.dist-info/top_level.txt
glinski-0.4.0.dist-info/RECORD
