Metadata-Version: 2.1
Name: glinski
Version: 0.4.0
Summary: Gliński's chess
Author-email: Johannes <johannes-programming@posteo.org>
License: The MIT License (MIT)
Project-URL: Download, https://pypi.org/project/glinski/#files
Project-URL: Source, https://github.com/johannes-programming/glinski
Classifier: License :: OSI Approved :: MIT License
Classifier: Programming Language :: Python
Classifier: Programming Language :: Python :: 3
Requires-Python: >=3.11
License-File: LICENSE.txt
Requires-Dist: isometric >=1.3
